ailib/__init__.py
ailib/cli.py
ailib/mcp.py
ailib/common/__init__.py
ailib/kfish/__init__.py
aicli-99.0.202511130646.dist-info/METADATA
aicli-99.0.202511130646.dist-info/WHEEL
aicli-99.0.202511130646.dist-info/entry_points.txt
aicli-99.0.202511130646.dist-info/top_level.txt
aicli-99.0.202511130646.dist-info/RECORD
